{
  "version": "7",
  "dialect": "postgresql",
  "entries": [
    {
      "idx": 0,
      "version": "7",
      "when": 1773715229112,
      "tag": "0000_silent_charles_xavier",
      "breakpoints": true
    },
    {
      "idx": 1,
      "version": "7",
      "when": 1774367843467,
      "tag": "0001_bright_whistler",
      "breakpoints": true
    },
    {
      "idx": 2,
      "version": "7",
      "when": 1774370139259,
      "tag": "0002_tranquil_switch",
      "breakpoints": true
    },
    {
      "idx": 3,
      "version": "7",
      "when": 1774382411570,
      "tag": "0003_enable_rls",
      "breakpoints": true
    },
    {
      "idx": 4,
      "version": "7",
      "when": 1774386663391,
      "tag": "0004_magical_wong",
      "breakpoints": true
    },
    {
      "idx": 5,
      "version": "7",
      "when": 1774390000000,
      "tag": "0005_security_sub_type",
      "breakpoints": true
    }
  ]
}